<annotation>
	<folder>JPEGImages</folder>
	<filename>yolo-1461.jpg</filename>
	<path>C:\pyworkplace\VOCdevkit\VOC2007\JPEGImages\yolo-1461.jpg</path>
	<source>
		<database>Unknown</database>
	</source>
	<size>
		<width>1920</width>
		<height>1080</height>
		<depth>3</depth>
	</size>
	<segmented>0</segmented>
	<object>
		<name>helmet</name>
		<pose>Unspecified</pose>
		<truncated>0</truncated>
		<difficult>0</difficult>
		<bndbox>
			<xmin>1811</xmin>
			<ymin>305</ymin>
			<xmax>1829</xmax>
			<ymax>327</ymax>
		</bndbox>
	</object>
	<object>
		<name>helmet</name>
		<pose>Unspecified</pose>
		<truncated>0</truncated>
		<difficult>0</difficult>
		<bndbox>
			<xmin>1344</xmin>
			<ymin>357</ymin>
			<xmax>1371</xmax>
			<ymax>388</ymax>
		</bndbox>
	</object>
	<object>
		<name>helmet</name>
		<pose>Unspecified</pose>
		<truncated>0</truncated>
		<difficult>0</difficult>
		<bndbox>
			<xmin>1353</xmin>
			<ymin>347</ymin>
			<xmax>1376</xmax>
			<ymax>378</ymax>
		</bndbox>
	</object>
	<object>
		<name>two_wheeler</name>
		<pose>Unspecified</pose>
		<truncated>0</truncated>
		<difficult>0</difficult>
		<bndbox>
			<xmin>1791</xmin>
			<ymin>295</ymin>
			<xmax>1849</xmax>
			<ymax>403</ymax>
		</bndbox>
	</object>
	<object>
		<name>two_wheeler</name>
		<pose>Unspecified</pose>
		<truncated>0</truncated>
		<difficult>0</difficult>
		<bndbox>
			<xmin>1303</xmin>
			<ymin>337</ymin>
			<xmax>1421</xmax>
			<ymax>526</ymax>
		</bndbox>
	</object>
</annotation>
