<annotation>
	<folder>JPEGImages</folder>
	<filename>yolo-165.jpg</filename>
	<path>C:\pyworkplace\VOCdevkit\VOC2007\JPEGImages\yolo-165.jpg</path>
	<source>
		<database>Unknown</database>
	</source>
	<size>
		<width>1920</width>
		<height>1080</height>
		<depth>3</depth>
	</size>
	<segmented>0</segmented>
	<object>
		<name>two_wheeler</name>
		<pose>Unspecified</pose>
		<truncated>1</truncated>
		<difficult>0</difficult>
		<bndbox>
			<xmin>1152</xmin>
			<ymin>675</ymin>
			<xmax>1754</xmax>
			<ymax>1080</ymax>
		</bndbox>
	</object>
	<object>
		<name>two_wheeler</name>
		<pose>Unspecified</pose>
		<truncated>0</truncated>
		<difficult>0</difficult>
		<bndbox>
			<xmin>805</xmin>
			<ymin>564</ymin>
			<xmax>967</xmax>
			<ymax>750</ymax>
		</bndbox>
	</object>
	<object>
		<name>two_wheeler</name>
		<pose>Unspecified</pose>
		<truncated>0</truncated>
		<difficult>0</difficult>
		<bndbox>
			<xmin>955</xmin>
			<ymin>577</ymin>
			<xmax>1060</xmax>
			<ymax>730</ymax>
		</bndbox>
	</object>
	<object>
		<name>two_wheeler</name>
		<pose>Unspecified</pose>
		<truncated>0</truncated>
		<difficult>0</difficult>
		<bndbox>
			<xmin>458</xmin>
			<ymin>639</ymin>
			<xmax>796</xmax>
			<ymax>1024</ymax>
		</bndbox>
	</object>
	<object>
		<name>two_wheeler</name>
		<pose>Unspecified</pose>
		<truncated>0</truncated>
		<difficult>0</difficult>
		<bndbox>
			<xmin>301</xmin>
			<ymin>631</ymin>
			<xmax>521</xmax>
			<ymax>952</ymax>
		</bndbox>
	</object>
	<object>
		<name>two_wheeler</name>
		<pose>Unspecified</pose>
		<truncated>1</truncated>
		<difficult>0</difficult>
		<bndbox>
			<xmin>5</xmin>
			<ymin>696</ymin>
			<xmax>427</xmax>
			<ymax>1080</ymax>
		</bndbox>
	</object>
	<object>
		<name>two_wheeler</name>
		<pose>Unspecified</pose>
		<truncated>0</truncated>
		<difficult>0</difficult>
		<bndbox>
			<xmin>470</xmin>
			<ymin>586</ymin>
			<xmax>585</xmax>
			<ymax>711</ymax>
		</bndbox>
	</object>
	<object>
		<name>helmet</name>
		<pose>Unspecified</pose>
		<truncated>0</truncated>
		<difficult>0</difficult>
		<bndbox>
			<xmin>1363</xmin>
			<ymin>691</ymin>
			<xmax>1452</xmax>
			<ymax>809</ymax>
		</bndbox>
	</object>
	<object>
		<name>helmet</name>
		<pose>Unspecified</pose>
		<truncated>0</truncated>
		<difficult>0</difficult>
		<bndbox>
			<xmin>1261</xmin>
			<ymin>672</ymin>
			<xmax>1357</xmax>
			<ymax>786</ymax>
		</bndbox>
	</object>
	<object>
		<name>helmet</name>
		<pose>Unspecified</pose>
		<truncated>0</truncated>
		<difficult>0</difficult>
		<bndbox>
			<xmin>914</xmin>
			<ymin>586</ymin>
			<xmax>941</xmax>
			<ymax>611</ymax>
		</bndbox>
	</object>
	<object>
		<name>without</name>
		<pose>Unspecified</pose>
		<truncated>0</truncated>
		<difficult>0</difficult>
		<bndbox>
			<xmin>891</xmin>
			<ymin>585</ymin>
			<xmax>914</xmax>
			<ymax>617</ymax>
		</bndbox>
	</object>
	<object>
		<name>without</name>
		<pose>Unspecified</pose>
		<truncated>0</truncated>
		<difficult>0</difficult>
		<bndbox>
			<xmin>982</xmin>
			<ymin>588</ymin>
			<xmax>1013</xmax>
			<ymax>616</ymax>
		</bndbox>
	</object>
	<object>
		<name>helmet</name>
		<pose>Unspecified</pose>
		<truncated>0</truncated>
		<difficult>0</difficult>
		<bndbox>
			<xmin>553</xmin>
			<ymin>661</ymin>
			<xmax>614</xmax>
			<ymax>730</ymax>
		</bndbox>
	</object>
	<object>
		<name>helmet</name>
		<pose>Unspecified</pose>
		<truncated>0</truncated>
		<difficult>0</difficult>
		<bndbox>
			<xmin>600</xmin>
			<ymin>715</ymin>
			<xmax>647</xmax>
			<ymax>765</ymax>
		</bndbox>
	</object>
	<object>
		<name>helmet</name>
		<pose>Unspecified</pose>
		<truncated>0</truncated>
		<difficult>0</difficult>
		<bndbox>
			<xmin>470</xmin>
			<ymin>652</ymin>
			<xmax>540</xmax>
			<ymax>722</ymax>
		</bndbox>
	</object>
	<object>
		<name>helmet</name>
		<pose>Unspecified</pose>
		<truncated>0</truncated>
		<difficult>0</difficult>
		<bndbox>
			<xmin>509</xmin>
			<ymin>594</ymin>
			<xmax>536</xmax>
			<ymax>624</ymax>
		</bndbox>
	</object>
	<object>
		<name>helmet</name>
		<pose>Unspecified</pose>
		<truncated>0</truncated>
		<difficult>0</difficult>
		<bndbox>
			<xmin>543</xmin>
			<ymin>597</ymin>
			<xmax>564</xmax>
			<ymax>625</ymax>
		</bndbox>
	</object>
	<object>
		<name>helmet</name>
		<pose>Unspecified</pose>
		<truncated>0</truncated>
		<difficult>0</difficult>
		<bndbox>
			<xmin>394</xmin>
			<ymin>634</ymin>
			<xmax>452</xmax>
			<ymax>706</ymax>
		</bndbox>
	</object>
	<object>
		<name>helmet</name>
		<pose>Unspecified</pose>
		<truncated>0</truncated>
		<difficult>0</difficult>
		<bndbox>
			<xmin>326</xmin>
			<ymin>658</ymin>
			<xmax>388</xmax>
			<ymax>717</ymax>
		</bndbox>
	</object>
	<object>
		<name>helmet</name>
		<pose>Unspecified</pose>
		<truncated>0</truncated>
		<difficult>0</difficult>
		<bndbox>
			<xmin>141</xmin>
			<ymin>725</ymin>
			<xmax>225</xmax>
			<ymax>816</ymax>
		</bndbox>
	</object>
	<object>
		<name>without</name>
		<pose>Unspecified</pose>
		<truncated>0</truncated>
		<difficult>0</difficult>
		<bndbox>
			<xmin>86</xmin>
			<ymin>739</ymin>
			<xmax>151</xmax>
			<ymax>812</ymax>
		</bndbox>
	</object>
	<object>
		<name>without</name>
		<pose>Unspecified</pose>
		<truncated>0</truncated>
		<difficult>0</difficult>
		<bndbox>
			<xmin>75</xmin>
			<ymin>699</ymin>
			<xmax>143</xmax>
			<ymax>766</ymax>
		</bndbox>
	</object>
</annotation>
