<annotation>
	<folder>JPEGImages</folder>
	<filename>yolo-1315.jpg</filename>
	<path>C:\pyworkplace\VOCdevkit\VOC2007\JPEGImages\yolo-1315.jpg</path>
	<source>
		<database>Unknown</database>
	</source>
	<size>
		<width>1920</width>
		<height>1080</height>
		<depth>3</depth>
	</size>
	<segmented>0</segmented>
	<object>
		<name>helmet</name>
		<pose>Unspecified</pose>
		<truncated>0</truncated>
		<difficult>0</difficult>
		<bndbox>
			<xmin>198</xmin>
			<ymin>515</ymin>
			<xmax>232</xmax>
			<ymax>546</ymax>
		</bndbox>
	</object>
	<object>
		<name>helmet</name>
		<pose>Unspecified</pose>
		<truncated>0</truncated>
		<difficult>0</difficult>
		<bndbox>
			<xmin>240</xmin>
			<ymin>547</ymin>
			<xmax>288</xmax>
			<ymax>611</ymax>
		</bndbox>
	</object>
	<object>
		<name>two_wheeler</name>
		<pose>Unspecified</pose>
		<truncated>0</truncated>
		<difficult>0</difficult>
		<bndbox>
			<xmin>168</xmin>
			<ymin>481</ymin>
			<xmax>252</xmax>
			<ymax>649</ymax>
		</bndbox>
	</object>
	<object>
		<name>two_wheeler</name>
		<pose>Unspecified</pose>
		<truncated>0</truncated>
		<difficult>0</difficult>
		<bndbox>
			<xmin>202</xmin>
			<ymin>539</ymin>
			<xmax>355</xmax>
			<ymax>856</ymax>
		</bndbox>
	</object>
</annotation>
