<annotation>
	<folder>JPEGImages</folder>
	<filename>yolo-302.jpg</filename>
	<path>C:\pyworkplace\VOCdevkit\VOC2007\JPEGImages\yolo-302.jpg</path>
	<source>
		<database>Unknown</database>
	</source>
	<size>
		<width>1920</width>
		<height>1080</height>
		<depth>3</depth>
	</size>
	<segmented>0</segmented>
	<object>
		<name>two_wheeler</name>
		<pose>Unspecified</pose>
		<truncated>0</truncated>
		<difficult>0</difficult>
		<bndbox>
			<xmin>380</xmin>
			<ymin>565</ymin>
			<xmax>663</xmax>
			<ymax>897</ymax>
		</bndbox>
	</object>
	<object>
		<name>two_wheeler</name>
		<pose>Unspecified</pose>
		<truncated>0</truncated>
		<difficult>0</difficult>
		<bndbox>
			<xmin>99</xmin>
			<ymin>555</ymin>
			<xmax>346</xmax>
			<ymax>866</ymax>
		</bndbox>
	</object>
	<object>
		<name>helmet</name>
		<pose>Unspecified</pose>
		<truncated>0</truncated>
		<difficult>0</difficult>
		<bndbox>
			<xmin>452</xmin>
			<ymin>578</ymin>
			<xmax>529</xmax>
			<ymax>652</ymax>
		</bndbox>
	</object>
	<object>
		<name>two_wheeler</name>
		<pose>Unspecified</pose>
		<truncated>0</truncated>
		<difficult>0</difficult>
		<bndbox>
			<xmin>299</xmin>
			<ymin>528</ymin>
			<xmax>391</xmax>
			<ymax>664</ymax>
		</bndbox>
	</object>
	<object>
		<name>two_wheeler</name>
		<pose>Unspecified</pose>
		<truncated>0</truncated>
		<difficult>0</difficult>
		<bndbox>
			<xmin>482</xmin>
			<ymin>512</ymin>
			<xmax>563</xmax>
			<ymax>660</ymax>
		</bndbox>
	</object>
	<object>
		<name>helmet</name>
		<pose>Unspecified</pose>
		<truncated>0</truncated>
		<difficult>0</difficult>
		<bndbox>
			<xmin>512</xmin>
			<ymin>530</ymin>
			<xmax>529</xmax>
			<ymax>555</ymax>
		</bndbox>
	</object>
	<object>
		<name>helmet</name>
		<pose>Unspecified</pose>
		<truncated>0</truncated>
		<difficult>0</difficult>
		<bndbox>
			<xmin>343</xmin>
			<ymin>532</ymin>
			<xmax>364</xmax>
			<ymax>556</ymax>
		</bndbox>
	</object>
	<object>
		<name>helmet</name>
		<pose>Unspecified</pose>
		<truncated>0</truncated>
		<difficult>0</difficult>
		<bndbox>
			<xmin>329</xmin>
			<ymin>544</ymin>
			<xmax>346</xmax>
			<ymax>560</ymax>
		</bndbox>
	</object>
	<object>
		<name>helmet</name>
		<pose>Unspecified</pose>
		<truncated>0</truncated>
		<difficult>0</difficult>
		<bndbox>
			<xmin>157</xmin>
			<ymin>581</ymin>
			<xmax>216</xmax>
			<ymax>633</ymax>
		</bndbox>
	</object>
</annotation>
