<annotation>
	<folder>JPEGImages</folder>
	<filename>yolo-1203.jpg</filename>
	<path>C:\pyworkplace\VOCdevkit\VOC2007\JPEGImages\yolo-1203.jpg</path>
	<source>
		<database>Unknown</database>
	</source>
	<size>
		<width>1920</width>
		<height>1080</height>
		<depth>3</depth>
	</size>
	<segmented>0</segmented>
	<object>
		<name>two_wheeler</name>
		<pose>Unspecified</pose>
		<truncated>1</truncated>
		<difficult>0</difficult>
		<bndbox>
			<xmin>996</xmin>
			<ymin>716</ymin>
			<xmax>1413</xmax>
			<ymax>1080</ymax>
		</bndbox>
	</object>
	<object>
		<name>two_wheeler</name>
		<pose>Unspecified</pose>
		<truncated>0</truncated>
		<difficult>0</difficult>
		<bndbox>
			<xmin>7</xmin>
			<ymin>581</ymin>
			<xmax>129</xmax>
			<ymax>836</ymax>
		</bndbox>
	</object>
	<object>
		<name>without</name>
		<pose>Unspecified</pose>
		<truncated>0</truncated>
		<difficult>0</difficult>
		<bndbox>
			<xmin>10</xmin>
			<ymin>603</ymin>
			<xmax>52</xmax>
			<ymax>655</ymax>
		</bndbox>
	</object>
	<object>
		<name>helmet</name>
		<pose>Unspecified</pose>
		<truncated>0</truncated>
		<difficult>0</difficult>
		<bndbox>
			<xmin>1173</xmin>
			<ymin>786</ymin>
			<xmax>1263</xmax>
			<ymax>899</ymax>
		</bndbox>
	</object>
	<object>
		<name>helmet</name>
		<pose>Unspecified</pose>
		<truncated>0</truncated>
		<difficult>0</difficult>
		<bndbox>
			<xmin>1079</xmin>
			<ymin>764</ymin>
			<xmax>1165</xmax>
			<ymax>877</ymax>
		</bndbox>
	</object>
</annotation>
