<annotation>
	<folder>JPEGImages</folder>
	<filename>yolo-344.jpg</filename>
	<path>C:\pyworkplace\VOCdevkit\VOC2007\JPEGImages\yolo-344.jpg</path>
	<source>
		<database>Unknown</database>
	</source>
	<size>
		<width>1920</width>
		<height>1080</height>
		<depth>3</depth>
	</size>
	<segmented>0</segmented>
	<object>
		<name>two_wheeler</name>
		<pose>Unspecified</pose>
		<truncated>0</truncated>
		<difficult>0</difficult>
		<bndbox>
			<xmin>271</xmin>
			<ymin>386</ymin>
			<xmax>365</xmax>
			<ymax>575</ymax>
		</bndbox>
	</object>
	<object>
		<name>two_wheeler</name>
		<pose>Unspecified</pose>
		<truncated>0</truncated>
		<difficult>0</difficult>
		<bndbox>
			<xmin>457</xmin>
			<ymin>380</ymin>
			<xmax>570</xmax>
			<ymax>562</ymax>
		</bndbox>
	</object>
	<object>
		<name>without</name>
		<pose>Unspecified</pose>
		<truncated>0</truncated>
		<difficult>0</difficult>
		<bndbox>
			<xmin>498</xmin>
			<ymin>381</ymin>
			<xmax>535</xmax>
			<ymax>431</ymax>
		</bndbox>
	</object>
	<object>
		<name>helmet</name>
		<pose>Unspecified</pose>
		<truncated>0</truncated>
		<difficult>0</difficult>
		<bndbox>
			<xmin>293</xmin>
			<ymin>391</ymin>
			<xmax>336</xmax>
			<ymax>436</ymax>
		</bndbox>
	</object>
</annotation>
